eduautoml/__init__.py
eduautoml/evaluation.py
eduautoml/model_selection.py
eduautoml/preprocessing.py
eduautoml/utils.py
eduautoml-0.1.dist-info/METADATA
eduautoml-0.1.dist-info/WHEEL
eduautoml-0.1.dist-info/entry_points.txt
eduautoml-0.1.dist-info/top_level.txt
eduautoml-0.1.dist-info/RECORD
